{
  "data": "2025-06-18",
  "ora_chiamata": "14:12",
  "ora_partenza_ambulanza": "14:15",
  "ora_arrivo_sul_posto": "14:27",
  "ora_partenza_dal_posto": "14:34",
  "ora_arrivo_ps": "14:44",
  "ora_rientro_sede": "14:56",
  "codice_uscita": "GIALLO",
  "codice_rientro": "VERDE",
  "tipo_mezzo": "BLS-CR-02",
  "numero_intervento": "1458",
  "indirizzo_intervento": "Via delle Ginestre 14",
  "via": "Via delle Ginestre",
  "numero_civico": "14",
  "citta": "Roma",
  "provincia": "RM",
  "cap": "00172",
  "telefono_chiamante": "3391122334",
  "cognome_nome_paziente": "Bianchi Alessandro",
  "sesso": "M",
  "data_nascita": "2009-03-12",
  "eta": "16",
  "luogo_nascita": "Roma",
  "provincia_nascita": "RM",
  "residenza": "Via delle Ortensie 10",
  "indirizzo_residenza": "Via delle Ortensie 10",
  "citta_residenza": "Roma",
  "provincia_residenza": "RM",
  "codice_fiscale": "BNCLSN09C12H501X",
  "nome_chiamante": "Marco",
  "cognome_chiamante": "Bianchi",
  "relazione_con_paziente": "Padre",
  "stato_coscienza": "vigile",
  "sintomi": ["dolore toracico", "dispnea"],
  "dolore_localizzato": "torace sinistro",
  "allergie": "nessuna nota",
  "patologie_pregresse": "asma bronchiale",
  "farmaci_assunti": "salbutamolo spray",
  "parametri_vitali": [
    {
      "tempo_rilevazione": "14:28",
      "frequenza_cardiaca": "108",
      "pressione_arteriosa": "125/80",
      "frequenza_respiratoria": "24",
      "saturazione_ossigeno": "94",
      "glicemia": "92",
      "temperatura": "36.9",
      "AVPU": "A",
      "pupille_PEARL": "sì",
      "ECG": "ritmo sinusale"
    }
  ],
  "ossigenoterapia": "sì",
  "flusso_ossigeno": "4 L/min",
  "farmaci_somministrati": [],
  "accesso_venoso": "no",
  "soluzione_endovenosa": "",
  "immobilizzazioni": "no",
  "monitoraggio_continuo": "sì",
  "mezzo_trasporto": "ambulanza BLS",
  "posizionamento_paziente": "decubito supino",
  "ospedale_destinazione": "Ospedale Sandro Pertini",
  "reparto_destinazione": "Medicina d'Urgenza",
  "paziente_rifiuto_trasporto": false,
  "forze_dell'ordine_presenti": null,
  "decesso_sul_posto": false,
  "paziente_consegnato_ps": true,
  "condizioni_consegna": "stabili",
  "nome_soccorritore_1": "Lucia Ferri",
  "ruolo_soccorritore_1": "autista soccorritore",
  "nome_soccorritore_2": "Matteo Ricci",
  "ruolo_soccorritore_2": "caposquadra",
  "nome_soccorritore_3": "Elena Neri",
  "ruolo_soccorritore_3": "soccorritrice",
  "firma_responsabile": "firma digitale acquisita",
  "note_intervento": "paziente collaborante, famiglia informata",
  "problemi_riscontrati": ""
}
